mzn_bench/__init__.py
mzn_bench/analysis/__init__.py
mzn_bench/analysis/analyse_changes.py
mzn_bench/analysis/collect.py
mzn_bench/analysis/plot.py
mzn_bench/analysis/report_status.py
mzn_bench/cli.py
mzn_bench/mzn_slurm.py
mzn_bench/pytest/__init__.py
mzn_bench/pytest/check_solutions.py
mzn_bench/pytest/check_statuses.py
mzn_bench-0.2.0.dist-info/METADATA
mzn_bench-0.2.0.dist-info/WHEEL
mzn_bench-0.2.0.dist-info/entry_points.txt
mzn_bench-0.2.0.dist-info/RECORD
