Metadata-Version: 2.1
Name: mzn-bench
Version: 0.2.0
Summary: SLURM scheduling functionality and a collection of scripts to process the resulting data
License: MPL-2.0
Author: Jip J. Dekker
Author-email: jip.dekker@monash.edu
Requires-Python: >=3.8,<4.0
Classifier: License :: OSI Approved
Classifier: Programming Language :: Python :: 3
Classifier: Programming Language :: Python :: 3.8
Classifier: Programming Language :: Python :: 3.9
Classifier: Programming Language :: Python :: 3.10
Classifier: Programming Language :: Python :: 3.11
Provides-Extra: plotting
Provides-Extra: scripts
Requires-Dist: bokeh (>=3,<4) ; extra == "plotting"
Requires-Dist: click (>=8.1,<9.0)
Requires-Dist: minizinc (>=0.9,<0.10)
Requires-Dist: pandas (>=2.0,<3.0) ; extra == "scripts"
Requires-Dist: ruamel-yaml (>=0.17,<0.18)
Requires-Dist: tabulate (>=0.9,<0.10) ; extra == "scripts"
